test/__init__.py
test/test_argparse.py
test/test_hmm.py
HyperParamManage-0.0.1.dist-info/METADATA
HyperParamManage-0.0.1.dist-info/WHEEL
HyperParamManage-0.0.1.dist-info/top_level.txt
HyperParamManage-0.0.1.dist-info/RECORD
