Metadata-Version: 2.1
Name: HyperParamManage
Version: 0.0.1
Summary: Hyper-parameters Management for Deep Learning Experiments.
Home-page: UNKNOWN
Author: Zhangzhi Peng
Author-email: <zhangzhipengcs@outlook.com>
License: UNKNOWN
Keywords: python,hyper-parameters,deep learning,machine learning
Platform: UNKNOWN
Classifier: Development Status :: 3 - Alpha
Classifier: Intended Audience :: Education
Classifier: Programming Language :: Python :: 3
Classifier: Operating System :: MacOS :: MacOS X
Classifier: Operating System :: Microsoft :: Windows
